medialog.abovecontentportlets-1.1.1-nspkg.pth
medialog/.DS_Store
medialog/abovecontentportlets/.DS_Store
medialog/abovecontentportlets/__init__.py
medialog/abovecontentportlets/aboveportlets.pt
medialog/abovecontentportlets/belowportlets.pt
medialog/abovecontentportlets/configure.zcml
medialog/abovecontentportlets/interfaces.py
medialog/abovecontentportlets/setuphandlers.py
medialog/abovecontentportlets/viewlets.py
medialog/abovecontentportlets/profiles/.DS_Store
medialog/abovecontentportlets/profiles/default/browserlayer.xml
medialog/abovecontentportlets/profiles/default/metadata.xml
medialog/abovecontentportlets/profiles/default/portlets.xml
medialog/abovecontentportlets/profiles/uninstall/browserlayer.xml
medialog/abovecontentportlets/profiles/uninstall/portlets.xml
medialog.abovecontentportlets-1.1.1.dist-info/METADATA
medialog.abovecontentportlets-1.1.1.dist-info/WHEEL
medialog.abovecontentportlets-1.1.1.dist-info/entry_points.txt
medialog.abovecontentportlets-1.1.1.dist-info/namespace_packages.txt
medialog.abovecontentportlets-1.1.1.dist-info/top_level.txt
medialog.abovecontentportlets-1.1.1.dist-info/RECORD
